odoo/addons/donation_base/README.rst
odoo/addons/donation_base/__init__.py
odoo/addons/donation_base/__manifest__.py
odoo/addons/donation_base/data/donation_mail_template.xml
odoo/addons/donation_base/data/donation_tax_seq.xml
odoo/addons/donation_base/demo/donation_demo.xml
odoo/addons/donation_base/i18n/de.po
odoo/addons/donation_base/i18n/donation_base.pot
odoo/addons/donation_base/i18n/es.po
odoo/addons/donation_base/i18n/fr.po
odoo/addons/donation_base/i18n/it.po
odoo/addons/donation_base/models/__init__.py
odoo/addons/donation_base/models/donation_tax_receipt.py
odoo/addons/donation_base/models/product.py
odoo/addons/donation_base/models/res_partner.py
odoo/addons/donation_base/readme/CONFIGURE.rst
odoo/addons/donation_base/readme/CONTRIBUTORS.rst
odoo/addons/donation_base/readme/DESCRIPTION.rst
odoo/addons/donation_base/report/report.xml
odoo/addons/donation_base/report/report_donationtax.xml
odoo/addons/donation_base/security/ir.model.access.csv
odoo/addons/donation_base/security/tax_receipt_security.xml
odoo/addons/donation_base/static/description/icon.png
odoo/addons/donation_base/static/description/index.html
odoo/addons/donation_base/tests/__init__.py
odoo/addons/donation_base/tests/test_donation_tax_receipt.py
odoo/addons/donation_base/views/donation_tax_receipt.xml
odoo/addons/donation_base/views/product.xml
odoo/addons/donation_base/views/res_partner.xml
odoo/addons/donation_base/wizard/__init__.py
odoo/addons/donation_base/wizard/tax_receipt_annual_create.py
odoo/addons/donation_base/wizard/tax_receipt_annual_create_view.xml
odoo/addons/donation_base/wizard/tax_receipt_print.py
odoo/addons/donation_base/wizard/tax_receipt_print_view.xml
odoo14_addon_donation_base-14.0.1.4.0.dist-info/METADATA
odoo14_addon_donation_base-14.0.1.4.0.dist-info/WHEEL
odoo14_addon_donation_base-14.0.1.4.0.dist-info/top_level.txt
odoo14_addon_donation_base-14.0.1.4.0.dist-info/RECORD
